kubeflow_trainer_api/__init__.py
kubeflow_trainer_api/models/__init__.py
kubeflow_trainer_api/models/io_k8s_api_autoscaling_v2_container_resource_metric_source.py
kubeflow_trainer_api/models/io_k8s_api_autoscaling_v2_container_resource_metric_status.py
kubeflow_trainer_api/models/io_k8s_api_autoscaling_v2_cross_version_object_reference.py
kubeflow_trainer_api/models/io_k8s_api_autoscaling_v2_external_metric_source.py
kubeflow_trainer_api/models/io_k8s_api_autoscaling_v2_external_metric_status.py
kubeflow_trainer_api/models/io_k8s_api_autoscaling_v2_horizontal_pod_autoscaler.py
kubeflow_trainer_api/models/io_k8s_api_autoscaling_v2_horizontal_pod_autoscaler_behavior.py
kubeflow_trainer_api/models/io_k8s_api_autoscaling_v2_horizontal_pod_autoscaler_condition.py
kubeflow_trainer_api/models/io_k8s_api_autoscaling_v2_horizontal_pod_autoscaler_list.py
kubeflow_trainer_api/models/io_k8s_api_autoscaling_v2_horizontal_pod_autoscaler_spec.py
kubeflow_trainer_api/models/io_k8s_api_autoscaling_v2_horizontal_pod_autoscaler_status.py
kubeflow_trainer_api/models/io_k8s_api_autoscaling_v2_hpa_scaling_policy.py
kubeflow_trainer_api/models/io_k8s_api_autoscaling_v2_hpa_scaling_rules.py
kubeflow_trainer_api/models/io_k8s_api_autoscaling_v2_metric_identifier.py
kubeflow_trainer_api/models/io_k8s_api_autoscaling_v2_metric_spec.py
kubeflow_trainer_api/models/io_k8s_api_autoscaling_v2_metric_status.py
kubeflow_trainer_api/models/io_k8s_api_autoscaling_v2_metric_target.py
kubeflow_trainer_api/models/io_k8s_api_autoscaling_v2_metric_value_status.py
kubeflow_trainer_api/models/io_k8s_api_autoscaling_v2_object_metric_source.py
kubeflow_trainer_api/models/io_k8s_api_autoscaling_v2_object_metric_status.py
kubeflow_trainer_api/models/io_k8s_api_autoscaling_v2_pods_metric_source.py
kubeflow_trainer_api/models/io_k8s_api_autoscaling_v2_pods_metric_status.py
kubeflow_trainer_api/models/io_k8s_api_autoscaling_v2_resource_metric_source.py
kubeflow_trainer_api-2.0.1.dist-info/METADATA
kubeflow_trainer_api-2.0.1.dist-info/WHEEL
kubeflow_trainer_api-2.0.1.dist-info/RECORD
